geode_viewableobjects/__init__.py
geode_viewableobjects/geode_viewableobjects_py_conversion.cpython-38-x86_64-linux-gnu.so
geode_viewableobjects/geode_viewableobjects_py_qem_proxy.cpython-38-x86_64-linux-gnu.so
geode_viewableobjects/libGeode-ViewableObjects_conversion.so
geode_viewableobjects/libGeode-ViewableObjects_qem_proxy.so
Geode_ViewableObjects-1.4.3.dist-info/METADATA
Geode_ViewableObjects-1.4.3.dist-info/WHEEL
Geode_ViewableObjects-1.4.3.dist-info/top_level.txt
Geode_ViewableObjects-1.4.3.dist-info/RECORD
