Metadata-Version: 2.1
Name: Geode-ViewableObjects
Version: 1.4.3
Summary: Geode module to objects visualization
Home-page: https://github.com/Geode-solutions/Geode-ViewableObjects
Author: Geode-solutions
Author-email: contact@geode-solutions.com
License: MIT
Classifier: License :: OSI Approved :: MIT License
Requires-Dist: OpenGeode-core (==13.*,>=13.0.1)
Requires-Dist: OpenGeode-IO (==5.*,>=5.24.0)
Requires-Dist: OpenGeode-Geosciences (==6.*,>=6.0.0)
Requires-Dist: OpenGeode-GeosciencesIO (==3.*,>=3.13.0)
Requires-Dist: Geode-Common (==24.*,>=24.0.0)
